MapSyncer/__init__.py
MapSyncer/app.py
MapSyncer/config.py
MapSyncer/run.py
MapSyncer/components/__init__.py
MapSyncer/components/common_models.py
MapSyncer/components/constants.py
MapSyncer/components/download.py
MapSyncer/components/get_exif.py
MapSyncer/components/osc_api_config.py
MapSyncer/components/osc_api_gateway.py
MapSyncer/components/osc_api_models.py
MapSyncer/components/ssl.py
MapSyncer/components/storage.py
MapSyncer/components/version_.py
MapSyncer/components/parsers/__init__.py
MapSyncer/components/parsers/base.py
MapSyncer/components/parsers/exif/__init__.py
MapSyncer/components/parsers/exif/exif.py
MapSyncer/components/parsers/exif/utils.py
MapSyncer/components/parsers/osc_metadata/__init__.py
MapSyncer/components/parsers/osc_metadata/parser.py
MapSyncer/static/__init__.py
MapSyncer/static/app.js
MapSyncer/static/edit-sequence.js
MapSyncer/static/global.js
MapSyncer/static/mapilio_fav.png
MapSyncer/static/osm_ico.png
MapSyncer/templates/__init__.py
MapSyncer/templates/details.html
MapSyncer/templates/display-sequence.html
MapSyncer/templates/kartaview-login.html
MapSyncer/templates/mapilio-login.html
MapSyncer/templates/sequence-edit.html
mapsyncer-1.0.4.dist-info/LICENSE
mapsyncer-1.0.4.dist-info/METADATA
mapsyncer-1.0.4.dist-info/WHEEL
mapsyncer-1.0.4.dist-info/entry_points.txt
mapsyncer-1.0.4.dist-info/top_level.txt
mapsyncer-1.0.4.dist-info/RECORD
