Metadata-Version: 2.1
Name: mapsyncer
Version: 1.0.4
Summary: A toolkit to download and upload the data from KartaView to Mapilio
Home-page: https://github.com/mapilio/MapSyncer
Author: Mapilio
License: MIT License
Requires-Python: >=3.6
License-File: LICENSE
Requires-Dist: mapilio-kit
Requires-Dist: ExifRead
Requires-Dist: calculation-mapilio==0.1.39
Requires-Dist: requests-oauthlib
Requires-Dist: imagesize
Requires-Dist: setuptools
Requires-Dist: psutil
Requires-Dist: flask
Requires-Dist: python-dotenv
Requires-Dist: osm-login-python
